{
  "generatedAt": "2026-01-29T21:50:27.893Z",
  "source": "stooq",
  "items": [
    {
      "sym": "spy.us",
      "name": "S&P 500",
      "group": "Index",
      "date": "2026-01-29",
      "close": 693.97,
      "prevDate": "2026-01-28",
      "prevClose": 695.42,
      "deltaPct": -0.2085070892410279,
      "ok": true
    },
    {
      "sym": "qqq.us",
      "name": "Nasdaq 100",
      "group": "Index",
      "date": "2026-01-29",
      "close": 629.32,
      "prevDate": "2026-01-28",
      "prevClose": 633.22,
      "deltaPct": -0.61589968731246,
      "ok": true
    },
    {
      "sym": "iwm.us",
      "name": "Russell 2000",
      "group": "Index",
      "date": "2026-01-29",
      "close": 263.37,
      "prevDate": "2026-01-28",
      "prevClose": 263.3,
      "deltaPct": 0.02658564375237482,
      "ok": true
    },
    {
      "sym": "dia.us",
      "name": "Dow 30",
      "group": "Index",
      "date": "2026-01-29",
      "close": 490.16,
      "prevDate": "2026-01-28",
      "prevClose": 490.13,
      "deltaPct": 0.006120825087219117,
      "ok": true
    },
    {
      "sym": "^hsi",
      "name": "Hong Kong HSI",
      "group": "Index",
      "date": "2026-01-29",
      "close": 27968.09,
      "prevDate": "2026-01-28",
      "prevClose": 27826.91,
      "deltaPct": 0.5073506185199861,
      "ok": true
    },
    {
      "sym": "^nkx",
      "name": "Japan Nikkei",
      "group": "Index",
      "date": "2026-01-29",
      "close": 53375.6,
      "prevDate": "2026-01-28",
      "prevClose": 53358.71,
      "deltaPct": 0.0316536887791985,
      "ok": true
    },
    {
      "sym": "^snx",
      "name": "Sensex India",
      "group": "Index",
      "date": "2026-01-29",
      "close": 82566.37,
      "prevDate": "2026-01-28",
      "prevClose": 82344.68,
      "deltaPct": 0.26922200681331887,
      "ok": true
    },
    {
      "sym": "^dax",
      "name": "DAX Germany",
      "group": "Index",
      "date": "2026-01-29",
      "close": 24293.24,
      "prevDate": "2026-01-28",
      "prevClose": 24822.79,
      "deltaPct": -2.1333218385201635,
      "ok": true
    },
    {
      "sym": "^ukx",
      "name": "FTSE 100 UK",
      "group": "Index",
      "date": "2026-01-29",
      "close": 10171.8,
      "prevDate": "2026-01-28",
      "prevClose": 10154.43,
      "deltaPct": 0.17105834596327085,
      "ok": true
    },
    {
      "sym": "aapl.us",
      "name": "Apple",
      "group": "Mega",
      "date": "2026-01-29",
      "close": 258.195,
      "prevDate": "2026-01-28",
      "prevClose": 256.44,
      "deltaPct": 0.6843706130089,
      "ok": true
    },
    {
      "sym": "msft.us",
      "name": "Microsoft",
      "group": "Mega",
      "date": "2026-01-29",
      "close": 433.48,
      "prevDate": "2026-01-28",
      "prevClose": 481.63,
      "deltaPct": -9.997300832589328,
      "ok": true
    },
    {
      "sym": "nvda.us",
      "name": "Nvidia",
      "group": "Mega",
      "date": "2026-01-29",
      "close": 192.43,
      "prevDate": "2026-01-28",
      "prevClose": 191.52,
      "deltaPct": 0.47514619883040066,
      "ok": true
    },
    {
      "sym": "amzn.us",
      "name": "Amazon",
      "group": "Mega",
      "date": "2026-01-29",
      "close": 241.73,
      "prevDate": "2026-01-28",
      "prevClose": 243.01,
      "deltaPct": -0.5267272951730351,
      "ok": true
    },
    {
      "sym": "googl.us",
      "name": "Alphabet",
      "group": "Mega",
      "date": "2026-01-29",
      "close": 338.25,
      "prevDate": "2026-01-28",
      "prevClose": 336.01,
      "deltaPct": 0.666646825987316,
      "ok": true
    },
    {
      "sym": "meta.us",
      "name": "Meta",
      "group": "Mega",
      "date": "2026-01-29",
      "close": 738.58,
      "prevDate": "2026-01-28",
      "prevClose": 668.73,
      "deltaPct": 10.445172192065556,
      "ok": true
    },
    {
      "sym": "tsla.us",
      "name": "Tesla",
      "group": "Mega",
      "date": "2026-01-29",
      "close": 416.35,
      "prevDate": "2026-01-28",
      "prevClose": 431.46,
      "deltaPct": -3.502062763639724,
      "ok": true
    },
    {
      "sym": "jpm.us",
      "name": "JPMorgan Chase",
      "group": "Large",
      "date": "2026-01-29",
      "close": 306.01,
      "prevDate": "2026-01-28",
      "prevClose": 300.77,
      "deltaPct": 1.742195032749283,
      "ok": true
    },
    {
      "sym": "wmt.us",
      "name": "Walmart",
      "group": "Large",
      "date": "2026-01-29",
      "close": 117.38,
      "prevDate": "2026-01-28",
      "prevClose": 116.57,
      "deltaPct": 0.6948614566355094,
      "ok": true
    },
    {
      "sym": "jnj.us",
      "name": "Johnson & Johnson",
      "group": "Large",
      "date": "2026-01-29",
      "close": 227.25,
      "prevDate": "2026-01-28",
      "prevClose": 227.72,
      "deltaPct": -0.2063938169682089,
      "ok": true
    },
    {
      "sym": "pg.us",
      "name": "Procter & Gamble",
      "group": "Large",
      "date": "2026-01-29",
      "close": 149.9,
      "prevDate": "2026-01-28",
      "prevClose": 147.34,
      "deltaPct": 1.737477942174559,
      "ok": true
    },
    {
      "sym": "xom.us",
      "name": "Exxon Mobil",
      "group": "Large",
      "date": "2026-01-29",
      "close": 140.51,
      "prevDate": "2026-01-28",
      "prevClose": 137.58,
      "deltaPct": 2.129670010175877,
      "ok": true
    },
    {
      "sym": "hd.us",
      "name": "Home Depot",
      "group": "Large",
      "date": "2026-01-29",
      "close": 371.72,
      "prevDate": "2026-01-28",
      "prevClose": 375.3,
      "deltaPct": -0.9539035438316024,
      "ok": true
    },
    {
      "sym": "xlk.us",
      "name": "Tech",
      "group": "Sector",
      "date": "2026-01-29",
      "close": 146.825,
      "prevDate": "2026-01-28",
      "prevClose": 149.23,
      "deltaPct": -1.6116062453930158,
      "ok": true
    },
    {
      "sym": "xlf.us",
      "name": "Financials",
      "group": "Sector",
      "date": "2026-01-29",
      "close": 53.54,
      "prevDate": "2026-01-28",
      "prevClose": 52.99,
      "deltaPct": 1.0379316852236142,
      "ok": true
    },
    {
      "sym": "xle.us",
      "name": "Energy",
      "group": "Sector",
      "date": "2026-01-29",
      "close": 50.51,
      "prevDate": "2026-01-28",
      "prevClose": 50.05,
      "deltaPct": 0.9190809190809279,
      "ok": true
    },
    {
      "sym": "xly.us",
      "name": "Consumer Disc",
      "group": "Sector",
      "date": "2026-01-29",
      "close": 121.18,
      "prevDate": "2026-01-28",
      "prevClose": 121.77,
      "deltaPct": -0.4845199967151048,
      "ok": true
    },
    {
      "sym": "xlp.us",
      "name": "Consumser Staples",
      "group": "Sector",
      "date": "2026-01-29",
      "close": 82.13,
      "prevDate": "2026-01-28",
      "prevClose": 82.32,
      "deltaPct": -0.23080660835762545,
      "ok": true
    },
    {
      "sym": "xli.us",
      "name": "Industrials",
      "group": "Sector",
      "date": "2026-01-29",
      "close": 165.82,
      "prevDate": "2026-01-28",
      "prevClose": 164.14,
      "deltaPct": 1.0235165102960853,
      "ok": true
    },
    {
      "sym": "xlv.us",
      "name": "Health Care",
      "group": "Sector",
      "date": "2026-01-29",
      "close": 153.81,
      "prevDate": "2026-01-28",
      "prevClose": 154.31,
      "deltaPct": -0.3240230704426139,
      "ok": true
    },
    {
      "sym": "xlu.us",
      "name": "Utilities",
      "group": "Sector",
      "date": "2026-01-29",
      "close": 43.325,
      "prevDate": "2026-01-28",
      "prevClose": 43.33,
      "deltaPct": -0.01153934918070032,
      "ok": true
    },
    {
      "sym": "xlb.us",
      "name": "Materials",
      "group": "Sector",
      "date": "2026-01-29",
      "close": 50.005,
      "prevDate": "2026-01-28",
      "prevClose": 49.95,
      "deltaPct": 0.11011011011010652,
      "ok": true
    },
    {
      "sym": "xlc.us",
      "name": "Communcation",
      "group": "Sector",
      "date": "2026-01-29",
      "close": 119.79,
      "prevDate": "2026-01-28",
      "prevClose": 116.75,
      "deltaPct": 2.603854389721638,
      "ok": true
    },
    {
      "sym": "xlre.us",
      "name": "Real Estate",
      "group": "Sector",
      "date": "2026-01-29",
      "close": 41.37,
      "prevDate": "2026-01-28",
      "prevClose": 40.85,
      "deltaPct": 1.2729498164014696,
      "ok": true
    },
    {
      "sym": "xauusd",
      "name": "Gold",
      "group": "Macro",
      "date": "2026-01-29",
      "close": 5388.27,
      "prevDate": "2026-01-28",
      "prevClose": 5415.17,
      "deltaPct": -0.49675264119131146,
      "ok": true
    },
    {
      "sym": "cb.f",
      "name": "Brent Oil",
      "group": "Macro",
      "date": "2026-01-29",
      "close": 69.6,
      "prevDate": null,
      "prevClose": null,
      "deltaPct": 0,
      "ok": true
    },
    {
      "sym": "10yusy.b",
      "name": "US 10Y Yield",
      "group": "Macro",
      "date": "2026-01-29",
      "close": 4.235,
      "prevDate": "2026-01-28",
      "prevClose": 4.244,
      "deltaPct": -0.2120640904806681,
      "ok": true
    },
    {
      "sym": "usdeur",
      "name": "USD/EUR",
      "group": "Macro",
      "date": "2026-01-29",
      "close": 0.835414,
      "prevDate": "2026-01-28",
      "prevClose": 0.836302,
      "deltaPct": -0.10618173817592558,
      "ok": true
    },
    {
      "sym": "btc.v",
      "name": "Bitcoin",
      "group": "Macro",
      "date": "2026-01-29",
      "close": 84403.01,
      "prevDate": "2026-01-28",
      "prevClose": 89297.81,
      "deltaPct": -5.481433419251836,
      "ok": true
    },
    {
      "sym": "hg.f",
      "name": "Copper",
      "group": "Macro",
      "date": "2026-01-29",
      "close": 627.37,
      "prevDate": null,
      "prevClose": null,
      "deltaPct": 0,
      "ok": true
    },
    {
      "sym": "si.f",
      "name": "Silver",
      "group": "Macro",
      "date": "2026-01-29",
      "close": 11574.3,
      "prevDate": null,
      "prevClose": null,
      "deltaPct": 0,
      "ok": true
    },
    {
      "sym": "ung.us",
      "name": "Nat Gas",
      "group": "Macro",
      "date": "2026-01-29",
      "close": 15.055,
      "prevDate": "2026-01-28",
      "prevClose": 14.53,
      "deltaPct": 3.6132140399174117,
      "ok": true
    },
    {
      "sym": "slx.us",
      "name": "Steel",
      "group": "Macro",
      "date": "2026-01-29",
      "close": 97.05,
      "prevDate": "2026-01-28",
      "prevClose": 95.86,
      "deltaPct": 1.2413936991445773,
      "ok": true
    }
  ]
}
