{
  "generatedAt": "2026-04-02T21:02:09.423Z",
  "source": "stooq",
  "items": [
    {
      "sym": "2yusy.b",
      "name": "US 2Y Yield",
      "group": null,
      "date": "2026-04-02",
      "close": 3.809,
      "prevDate": "2026-04-01",
      "prevClose": 3.813,
      "deltaPct": -0.10490427484920462,
      "history": [
        {
          "date": "2026-04-02",
          "close": 3.809
        }
      ],
      "ok": true
    },
    {
      "sym": "5yusy.b",
      "name": "US 5Y Yield",
      "group": null,
      "date": "2026-04-02",
      "close": 3.951,
      "prevDate": "2026-04-01",
      "prevClose": 3.96,
      "deltaPct": -0.2272727272727204,
      "history": [
        {
          "date": "2026-04-02",
          "close": 3.951
        }
      ],
      "ok": true
    },
    {
      "sym": "10yusy.b",
      "name": "US 10Y Yield",
      "group": null,
      "date": "2026-04-02",
      "close": 4.309,
      "prevDate": "2026-04-01",
      "prevClose": 4.322,
      "deltaPct": -0.3007866728366504,
      "history": [
        {
          "date": "2026-04-02",
          "close": 4.309
        }
      ],
      "ok": true
    },
    {
      "sym": "30yusy.b",
      "name": "US 30Y Yield",
      "group": null,
      "date": "2026-04-02",
      "close": 4.883,
      "prevDate": "2026-04-01",
      "prevClose": 4.902,
      "deltaPct": -0.3875968992248069,
      "history": [
        {
          "date": "2026-04-02",
          "close": 4.883
        }
      ],
      "ok": true
    },
    {
      "sym": "usdeur",
      "name": "USD/EUR",
      "group": null,
      "date": "2026-04-02",
      "close": 0.866686,
      "prevDate": "2026-04-01",
      "prevClose": 0.862909,
      "deltaPct": 0.4377054822698456,
      "history": [
        {
          "date": "2026-04-02",
          "close": 0.866686
        }
      ],
      "ok": true
    },
    {
      "sym": "cb.f",
      "name": "Brent Oil",
      "group": null,
      "date": "2026-04-02",
      "close": 108.85,
      "prevDate": "2026-04-01",
      "prevClose": 100.33,
      "deltaPct": 8.49197647762383,
      "history": [
        {
          "date": "2026-04-02",
          "close": 108.85
        }
      ],
      "ok": true
    },
    {
      "sym": "^spx",
      "name": "S&P 500",
      "group": null,
      "date": "2026-04-02",
      "close": 6582.7,
      "prevDate": "2026-04-01",
      "prevClose": 6575.3,
      "deltaPct": 0.1125423935029568,
      "history": [
        {
          "date": "2026-04-02",
          "close": 6582.7
        }
      ],
      "ok": true
    },
    {
      "sym": "xauusd",
      "name": "Gold",
      "group": null,
      "date": "2026-04-02",
      "close": 4676.3,
      "prevDate": "2026-04-01",
      "prevClose": 4758.19,
      "deltaPct": -1.7210325775137036,
      "history": [
        {
          "date": "2026-04-02",
          "close": 4676.3
        }
      ],
      "ok": true
    },
    {
      "sym": "asts.us",
      "name": "ASTS",
      "group": null,
      "date": "2026-04-02",
      "close": 92.49,
      "prevDate": "2026-04-01",
      "prevClose": 83.91,
      "deltaPct": 10.225241329996425,
      "history": [
        {
          "date": "2026-04-02",
          "close": 92.49
        }
      ],
      "ok": true
    }
  ]
}
